tests_metadata/__init__.py
tests_metadata/test_existence.py
time_series_metadata/__init__.py
time_series_metadata/scheme.py
time_series_metadata-0.1.1.dist-info/LICENSE
time_series_metadata-0.1.1.dist-info/METADATA
time_series_metadata-0.1.1.dist-info/WHEEL
time_series_metadata-0.1.1.dist-info/top_level.txt
time_series_metadata-0.1.1.dist-info/RECORD
