Metadata-Version: 2.1
Name: time-series-metadata
Version: 0.1.1
Summary: This package provides a Python implementation of a metadata scheme for time-series with measurement uncertainties.
Home-page: https://github.com/PTB-PSt1/time-series-metadata
Author: Maximilian Gruber, Björn Ludwig , Bang Xiang Yong , Benedikt Seeger
Author-email: bjoern.ludwig@ptb.de
License: UNKNOWN
Download-URL: https://github.com/PTB-PSt1/time-series-metadata/releases/download/v0.1.1/time-series-metadata-0.1.1.tar.gz
Project-URL: Documentation, https://time-series-metadata.readthedocs.io/en/v0.1.1/
Project-URL: Source, https://github.com/PTB-PSt1/time-series-metadata/tree/v0.1.1/
Project-URL: Tracker, https://github.com/PTB-PSt1/time-series-metadata/issues
Keywords: metadata time-series uncertainty metrology
Platform: UNKNOWN
Classifier: Topic :: Utilities
Classifier: Topic :: Scientific/Engineering
Classifier: Topic :: Software Development :: Libraries :: Python Modules
Classifier: Intended Audience :: Education
Classifier: Intended Audience :: Science/Research
Classifier: License :: OSI Approved :: GNU Lesser General Public License v3 or later (LGPLv3+)
Classifier: Programming Language :: Python :: 3
Classifier: Programming Language :: Python :: 3.5
Classifier: Programming Language :: Python :: 3.6
Classifier: Programming Language :: Python :: 3.7
Classifier: Programming Language :: Python :: 3.8
Classifier: Operating System :: OS Independent
Classifier: Typing :: Typed
Requires-Python: >=3.5
